ctube/__init__.py
ctube/app.py
ctube/callbacks.py
ctube/cli.py
ctube/cmds.py
ctube/colors.py
ctube/containers.py
ctube/download.py
ctube/errors.py
ctube/extractors.py
ctube/helpers.py
ctube/parser.py
ctube/paths.py
ctube/printers.py
ctube/terminal.py
ctube/update.py
ctube-0.2.0.dist-info/LICENSE
ctube-0.2.0.dist-info/METADATA
ctube-0.2.0.dist-info/WHEEL
ctube-0.2.0.dist-info/entry_points.txt
ctube-0.2.0.dist-info/RECORD
