Metadata-Version: 2.1
Name: ctube
Version: 0.2.0
Summary: 
Home-page: https://pypi.org/project/ctube/
License: MIT
Keywords: innertube,youtube,youtube-music,python,download,music,client
Author: Simone Gentili
Author-email: gensydev@gmail.com
Requires-Python: >=3.8,<4.0
Classifier: License :: OSI Approved :: MIT License
Classifier: Programming Language :: Python :: 3
Classifier: Programming Language :: Python :: 3.8
Classifier: Programming Language :: Python :: 3.9
Classifier: Programming Language :: Python :: 3.10
Classifier: Programming Language :: Python :: 3.11
Classifier: Programming Language :: Python :: 3.12
Requires-Dist: eyed3 (>=0.9.7,<0.10.0)
Requires-Dist: innertube (>=2.1.16,<3.0.0)
Requires-Dist: pathvalidate (>=3.2.0,<4.0.0)
Requires-Dist: pydub (>=0.25.1,<0.26.0)
Requires-Dist: pytubefix
Requires-Dist: requests (>=2.32.2,<3.0.0)
Project-URL: Repository, https://github.com/g3nsy/ctube
